lxml_asserts-0.1.1.dist-info/RECORD
lxml_asserts-0.1.1.dist-info/WHEEL
lxml_asserts-0.1.1.dist-info/metadata.json
lxml_asserts-0.1.1.dist-info/top_level.txt
lxml_asserts-0.1.1.dist-info/DESCRIPTION.rst
lxml_asserts-0.1.1.dist-info/METADATA
lxml_asserts/graph_utils.py
lxml_asserts/compat.py
lxml_asserts/testcase.py
lxml_asserts/__init__.py
